Combinational/ALU/4bit.v
module ALU_4bit(x, y, a, b, op);
    input [3:0] a, b, op;
    output reg [3:0] x, y;

    always @(a, b, op) begin
        case(op)
            4'b0000: x = {3'b000, |a};      // OR Reduction
            4'b0001: x = {3'b000, &a};      // AND Reduction
            4'b0010: x = {3'b000, ^a};      // XOR Reduction
            4'b0011: x = a & b;             // AND Operation
            4'b0100: x = a | b;             // OR Operation
            4'b0101: x = a ^ b;             // XOR Operation
            4'b0110: x = {3'b000, a > b};   // Greater Than
            4'b0111: x = {3'b000, a < b};   // Less Than
            4'b1000: x = {3'b000, !a};      // NOT Reduction
            4'b1001: x = {3'b000, a == b};  // Equality Check
            4'b1010: {y[0], x} = a + b;     // Addition (Carry in y[0])
            4'b1011: x = a - b;             // Subtraction
            4'b1100: {y, x} = a * b;        // Multiplication
            4'b1101: {y, x} = a >> b;       // Right Shift
            4'b1110: {y, x} = a << b;       // Left Shift
            4'b1111: x = ~a;                // Bitwise NOT
            default: $display("Error: Invalid op code");
        endcase
    end
endmodule

Combinational/ALU/tb.v
`timescale 1ns / 1ps
module ALU_4bit_tb;
    reg [3:0] a, b, op;
    wire [3:0] x, y;

    // Instantiate ALU
    ALU_4bit uut (.a(a), .b(b), .op(op), .x(x), .y(y));

    initial begin
        $dumpfile("ALU_4bit.vcd");
        $dumpvars(0, ALU_4bit_tb);

        $monitor("a=%b, b=%b, op=%b -> x=%b, y=%b", a, b, op, x, y);

        #0  a = 4'b1010; b = 4'b0101; op = 4'b0000; // OR Reduction
        #10 a = 4'b1101; b = 4'b0000; op = 4'b0001; // AND Reduction
        #10 a = 4'b1001; b = 4'b0110; op = 4'b0010; // XOR Reduction
        #10 a = 4'b1111; b = 4'b0011; op = 4'b0011; // AND
        #10 a = 4'b1100; b = 4'b0110; op = 4'b0100; // OR
        #10 a = 4'b0101; b = 4'b1010; op = 4'b0101; // XOR
        #10 a = 4'b1001; b = 4'b0111; op = 4'b0110; // Greater Than
        #10 a = 4'b0001; b = 4'b1010; op = 4'b0111; // Less Than
        #10 a = 4'b0011; b = 4'b0011; op = 4'b1001; // Equality
        #10 a = 4'b0110; b = 4'b0011; op = 4'b1010; // Addition
        #10 a = 4'b1001; b = 4'b0010; op = 4'b1011; // Subtraction
        #10 a = 4'b0011; b = 4'b0010; op = 4'b1100; // Multiplication
        #10 a = 4'b1100; b = 4'b0001; op = 4'b1101; // Right Shift
        #10 a = 4'b0011; b = 4'b0001; op = 4'b1110; // Left Shift
        #10 a = 4'b1100; b = 4'b0000; op = 4'b1111; // Bitwise NOT

        #10 $finish;
    end
endmodule

Combinational/ALU/ALU_4bit.vcd
$date
	Sun Feb 02 12:59:39 2025
$end
$version
	Icarus Verilog
$end
$timescale
	1ps
$end
$scope module ALU_4bit_tb $end
$var wire 4 ! x [3:0] $end
$var wire 4 " y [3:0] $end
$var reg 4 # a [3:0] $end
$var reg 4 $ b [3:0] $end
$var reg 4 % op [3:0] $end
$scope module uut $end
$var wire 4 & a [3:0] $end
$var wire 4 ' b [3:0] $end
$var wire 4 ( op [3:0] $end
$var reg 4 ) x [3:0] $end
$var reg 4 * y [3:0] $end
$upscope $end
$upscope $end
$enddefinitions $end
#0
$dumpvars
bx *
b1 )
b0 (
b101 '
b1010 &
b0 %
b101 $
b1010 #
bx "
b1 !
$end
#10000
b0 )
b0 !
b1 %
b1 (
b0 $
b0 '
b1101 #
b1101 &
#20000
b10 %
b10 (
b110 $
b110 '
b1001 #
b1001 &
#30000
b11 )
b11 !
b11 %
b11 (
b11 $
b11 '
b1111 #
b1111 &
#40000
b1110 )
b1110 !
b100 %
b100 (
b110 $
b110 '
b1100 #
b1100 &
#50000
b1111 )
b1111 !
b101 %
b101 (
b1010 $
b1010 '
b101 #
b101 &
#60000
b1 )
b1 !
b110 %
b110 (
b111 $
b111 '
b1001 #
b1001 &
#70000
b111 %
b111 (
b1010 $
b1010 '
b1 #
b1 &
#80000
b1001 %
b1001 (
b11 $
b11 '
b11 #
b11 &
#90000
bx0 *
bx0 "
b1001 )
b1001 !
b1010 %
b1010 (
b110 #
b110 &
#100000
b111 )
b111 !
b1011 %
b1011 (
b10 $
b10 '
b1001 #
b1001 &
#110000
b0 *
b0 "
b110 )
b110 !
b1100 %
b1100 (
b11 #
b11 &
#120000
b1101 %
b1101 (
b1 $
b1 '
b1100 #
b1100 &
#130000
b1110 %
b1110 (
b11 #
b11 &
#140000
b11 )
b11 !
b1111 %
b1111 (
b0 $
b0 '
b1100 #
b1100 &
