Sequntial/Latch And Flipflops/DFF/Behavioural_Basic.v
module Behavioural_Basic(q,d,clk);
input d,clk;
output reg q;
always@(posedge clk) //when clock changes on 0 to 1 , it is posedge triggered
  q=d;
endmodule

Sequntial/Latch And Flipflops/DFF/BB_tb.v
`timescale 1ns / 1ps

module Behavioural_Basic_tb;
    reg d, clk;
    wire q;
    
    // Instantiate the D Flip-Flop module
    Behavioural_Basic uut (.q(q), .d(d), .clk(clk));
    
    // Clock generation
    always #5 clk = ~clk; // Generate a clock with a period of 10ns

    initial begin
        $dumpfile("Behavioural_Basic.vcd");
        $dumpvars(0, Behavioural_Basic_tb);
        
        $monitor("Time=%0t | d=%b, clk=%b -> q=%b", $time, d, clk, q);
        
        // Initialize values
        clk = 0; d = 0;
        
        // Apply test cases
        #10 d = 1;  // Apply d=1, should update on next clock posedge
        #10 d = 0;  // Apply d=0, should update on next clock posedge
        #10 d = 1;  // Apply d=1, should update on next clock posedge
        #10 d = 0;  // Apply d=0, should update on next clock posedge
        #10 d = 1;  // Apply d=1, should update on next clock posedge
        
        #20 $finish; // End simulation
    end
endmodule

Sequntial/Latch And Flipflops/DFF/Behavioural_Basic.vcd
$date
	Mon Feb 03 10:38:16 2025
$end
$version
	Icarus Verilog
$end
$timescale
	1ps
$end
$scope module Behavioural_Basic_tb $end
$var wire 1 ! q $end
$var reg 1 " clk $end
$var reg 1 # d $end
$scope module uut $end
$var wire 1 $ clk $end
$var wire 1 % d $end
$var reg 1 & q $end
$upscope $end
$upscope $end
$enddefinitions $end
#0
$dumpvars
x&
0%
0$
0#
0"
x!
$end
#5000
0&
0!
1"
1$
#10000
0"
0$
1#
1%
#15000
1&
1!
1"
1$
#20000
0"
0$
0#
0%
#25000
0&
0!
1"
1$
#30000
0"
0$
1#
1%
#35000
1&
1!
1"
1$
#40000
0"
0$
0#
0%
#45000
0&
0!
1"
1$
#50000
0"
0$
1#
1%
#55000
1&
1!
1"
1$
