Sequntial/Latch And Flipflops/DFF/BB87.v
//Bheavioural Positive Edge Triggered DFF Asynchronous Active Low Reset and Active High set

module dff_PE_ARL_AHS(q, d, clk, rst, set);
    input d, clk, rst, set;
    output reg q;

    always @(posedge clk or negedge rst or posedge set) // Correct 'or' instead of ','
    begin
        if (!rst)       // Active low reset
            q <= 1'b0;
        else if (set)   // Active high set
            q <= 1'b1;
        else
            q <= d;     // Standard D-Flip-Flop operation
    end
endmodule

Sequntial/Latch And Flipflops/DFF/BB87_tb.v
`timescale 1ns / 1ps

module dff_PE_ARL_AHS_tb;
    reg d, clk, rst, set;
    wire q;
    
    // Instantiate the D Flip-Flop module
    dff_PE_ARL_AHS uut (.q(q), .d(d), .clk(clk), .rst(rst), .set(set));
    
    // Clock generation (10ns period -> 5ns high, 5ns low)
    always #5 clk = ~clk; 

    initial begin
        $dumpfile("dff_PE_ARL_AHS.vcd");
        $dumpvars(0, dff_PE_ARL_AHS_tb);
        
        $monitor("Time=%0t | d=%b, clk=%b, rst=%b, set=%b -> q=%b", $time, d, clk, rst, set, q);
        
        // Initialize values
        clk = 0; d = 0; rst = 1; set = 0;  // Start with reset deactivated

        // Test case 1: Apply active low reset
        #3  rst = 0;      // Assert reset (q should become 0)
        #7  rst = 1;      // Release reset

        // Test case 2: Normal flip-flop operation
        #10 d = 1;        // Apply d=1
        #10 d = 0;        // Apply d=0

        // Test case 3: Apply asynchronous set
        #10 set = 1;      // Set q=1 immediately
        #5  set = 0;      // Release set
        
        // Test case 4: Check normal operation after set
        #10 d = 1;
        #10 d = 0;

        // Test case 5: Apply reset while set is high (reset has priority)
        #10 rst = 0; set = 1;  // Reset should override set, q=0
        #5  rst = 1; set = 0;  // Release both

        // Test case 6: Check normal operation again
        #10 d = 1;
        #10 d = 0;
        
        #50 $finish;      // End simulation
    end
endmodule

Sequntial/Latch And Flipflops/DFF/dff_PE_ARL_AHS.vcd
$date
	Mon Feb 03 11:10:59 2025
$end
$version
	Icarus Verilog
$end
$timescale
	1ps
$end
$scope module dff_PE_ARL_AHS_tb $end
$var wire 1 ! q $end
$var reg 1 " clk $end
$var reg 1 # d $end
$var reg 1 $ rst $end
$var reg 1 % set $end
$scope module uut $end
$var wire 1 & clk $end
$var wire 1 ' d $end
$var wire 1 ( rst $end
$var wire 1 ) set $end
$var reg 1 * q $end
$upscope $end
$upscope $end
$enddefinitions $end
#0
$dumpvars
x*
0)
1(
0'
0&
0%
1$
0#
0"
x!
$end
#3000
0*
0!
0$
0(
#5000
1"
1&
#10000
0"
0&
1$
1(
#15000
1"
1&
#20000
0"
0&
1#
1'
#25000
1*
1!
1"
1&
#30000
0"
0&
0#
0'
#35000
0*
0!
1"
1&
#40000
1*
1!
0"
0&
1%
1)
#45000
0*
0!
1"
1&
0%
0)
#50000
0"
0&
#55000
1*
1!
1"
1&
1#
1'
#60000
0"
0&
#65000
0*
0!
1"
1&
0#
0'
#70000
0"
0&
#75000
1"
1&
1%
1)
0$
0(
#80000
0"
0&
0%
0)
1$
1(
#85000
1"
1&
#90000
0"
0&
1#
1'
#95000
1*
1!
1"
1&
#100000
0"
0&
0#
0'
#105000
0*
0!
1"
1&
