Sequntial/Latch And Flipflops/DFF/BB85.v
//Bheavioural Nehative Edge Triggered DFF Asynchronous Active High Reset

module dff_PN_ARH(q,d,clk,rst);
input d,clk,rst;
output reg q;
always@(negedge clk or posedge rst) //when clock changes on 0 to 1 , it is posedge triggered
    if(rst)
        q<=1'b0;
    else
        q<=d;
endmodule

Sequntial/Latch And Flipflops/DFF/BB85_tb.v
`timescale 1ns / 1ps

module dff_PN_ARH_tb;
    reg d, clk, rst;
    wire q;
    
    // Instantiate the D Flip-Flop module
    dff_PN_ARH uut (.q(q), .d(d), .clk(clk), .rst(rst));
    
    // Clock generation (10ns period -> 5ns high, 5ns low)
    always #5 clk = ~clk; 

    initial begin
        $dumpfile("dff_PN_ARH.vcd");
        $dumpvars(0, dff_PN_ARH_tb);
        
        $monitor("Time=%0t | d=%b, clk=%b, rst=%b -> q=%b", $time, d, clk, rst, q);
        
        // Initialize values
        clk = 0; d = 0; rst = 0;
        
        // Apply test cases
        #5  rst = 1;      // Assert reset at a negedge clk
        #10 rst = 0;      // Release reset at a negedge clk
        #10 d = 1;        // Apply d=1
        #10 d = 0;        // Apply d=0
        #10 rst = 1;      // Reset while d=0
        #10 rst = 0;      // Release reset
        #10 d = 1;        // Apply d=1
        #10 d = 0;        // Apply d=0
        #50 $finish;      // End simulation at 110ns
    end
endmodule

Sequntial/Latch And Flipflops/DFF/dff_PN_ARH.vcd
$date
	Mon Feb 03 10:59:10 2025
$end
$version
	Icarus Verilog
$end
$timescale
	1ps
$end
$scope module dff_PN_ARH_tb $end
$var wire 1 ! q $end
$var reg 1 " clk $end
$var reg 1 # d $end
$var reg 1 $ rst $end
$scope module uut $end
$var wire 1 % clk $end
$var wire 1 & d $end
$var wire 1 ' rst $end
$var reg 1 ( q $end
$upscope $end
$upscope $end
$enddefinitions $end
#0
$dumpvars
0(
0'
0&
0%
0$
0#
0"
0!
$end
#5000
1$
1'
1"
1%
#10000
0"
0%
#15000
1"
1%
0$
0'
#20000
0"
0%
#25000
1"
1%
1#
1&
#30000
1(
1!
0"
0%
#35000
1"
1%
0#
0&
#40000
0(
0!
0"
0%
#45000
1"
1%
1$
1'
#50000
0"
0%
#55000
1"
1%
0$
0'
#60000
0"
0%
#65000
1"
1%
1#
1&
#70000
1(
1!
0"
0%
#75000
1"
1%
0#
0&
#80000
0(
0!
0"
0%
