Sequntial/Latch And Flipflops/DFF/BB88.v
//Bheavioural Positive Edge Triggered DFF Synchronous Active High Reset

module dff_PE_SRH(q,d,clk,rst);
input d,clk,rst;
output reg q;
always@(posedge clk ) //when clock changes on 0 to 1 , it is posedge triggered
    if(rst)
        q<=1'b0;
    else
        q<=d;
endmodule

Sequntial/Latch And Flipflops/DFF/BB88_tb.v
`timescale 1ns / 1ps

module dff_PE_SRH_tb;
    reg d, clk, rst;
    wire q;
    
    // Instantiate the D Flip-Flop module
    dff_PE_SRH uut (.q(q), .d(d), .clk(clk), .rst(rst));
    
    // Clock generation (10ns period -> 5ns high, 5ns low)
    always #5 clk = ~clk; 

    initial begin
        $dumpfile("dff_PE_SRH.vcd");
        $dumpvars(0, dff_PE_SRH_tb);
        
        $monitor("Time=%0t | d=%b, clk=%b, rst=%b -> q=%b", $time, d, clk, rst, q);
        
        // Initialize values
        clk = 0; d = 0; rst = 0;  // Start with reset deactivated

        // Test case 1: Normal operation without reset
        #10 d = 1;  // d=1, should latch on posedge clk
        #10 d = 0;  // d=0, should latch on posedge clk

        // Test case 2: Apply synchronous reset
        #10 rst = 1;  // Set reset high (should take effect on next posedge clk)
        #10 rst = 0;  // Release reset

        // Test case 3: Check normal operation after reset
        #10 d = 1;
        #10 d = 0;

        // Test case 4: Check reset in between operation
        #10 rst = 1; d = 1;  // Reset while d=1 (should reset on next clk posedge)
        #10 rst = 0; d = 0;  // Release reset

        // Test case 5: Check normal behavior again
        #10 d = 1;
        #10 d = 0;
        
        #50 $finish;  // End simulation
    end
endmodule

Sequntial/Latch And Flipflops/DFF/dff_PE_SRH.vcd
$date
	Mon Feb 03 11:15:25 2025
$end
$version
	Icarus Verilog
$end
$timescale
	1ps
$end
$scope module dff_PE_SRH_tb $end
$var wire 1 ! q $end
$var reg 1 " clk $end
$var reg 1 # d $end
$var reg 1 $ rst $end
$scope module uut $end
$var wire 1 % clk $end
$var wire 1 & d $end
$var wire 1 ' rst $end
$var reg 1 ( q $end
$upscope $end
$upscope $end
$enddefinitions $end
#0
$dumpvars
x(
0'
0&
0%
0$
0#
0"
x!
$end
#5000
0(
0!
1"
1%
#10000
0"
0%
1#
1&
#15000
1(
1!
1"
1%
#20000
0"
0%
0#
0&
#25000
0(
0!
1"
1%
#30000
0"
0%
1$
1'
#35000
1"
1%
#40000
0"
0%
0$
0'
#45000
1"
1%
#50000
0"
0%
1#
1&
#55000
1(
1!
1"
1%
#60000
0"
0%
0#
0&
#65000
0(
0!
1"
1%
#70000
0"
0%
1#
1&
1$
1'
#75000
1"
1%
#80000
0"
0%
0#
0&
0$
0'
#85000
1"
1%
#90000
0"
0%
1#
1&
#95000
1(
1!
1"
1%
#100000
0"
0%
0#
0&
#105000
0(
0!
1"
1%
