Basics/Adders/Full Adder/FullAdder.v
module FullAdder(a,b,cin,cout,sum);
    input a;
    input b;
    input cin;
    output cout;
    output sum;
    wire N1,N2,N3,N4;
    xor xor1(N1,a,b);
    xor xor2(sum,N1,cin);
    and and1(N2,a,b);
    and and2(N3,b,cin);
    and and3(N4,cin,a);
    or or1(cout,N2,N3,N4);
endmodule

Combinational/4 Bit FA/Structural.v
module Structural(s, cout, a, b, cin);
    input [3:0] a, b;
    input cin;
    output [3:0] s;
    output cout;
    wire n1, n2, n3;

    FullAdder f1(.a(a[0]), .b(b[0]), .cin(cin), .sum(s[0]), .cout(n1));
    FullAdder f2(.a(a[1]), .b(b[1]), .cin(n1), .sum(s[1]), .cout(n2));
    FullAdder f3(.a(a[2]), .b(b[2]), .cin(n2), .sum(s[2]), .cout(n3));
    FullAdder f4(.a(a[3]), .b(b[3]), .cin(n3), .sum(s[3]), .cout(cout));
endmodule

Combinational/4 Bit FA/Structural_tb.v
`timescale 1ns/1ns

module Structural_tb;
reg [3:0]a,b;
reg cin;
wire [3:0]s;
wire cout;
Structural uut(s,cout,a,b,cin);
initial begin 
    $dumpfile("Structural_tb.vcd");
    $dumpvars(0,Structural_tb);

    $monitor("a=%b,b=%b,cin=%b,s=%b,cout=%b",a,b,cin,s,cout);
    a=4'b0000;b=4'b0000;cin=1'b0;

    #10 a=4'b0001;b=4'b0001;cin=1'b0;
    #10 a=4'b0010;b=4'b0010;cin=1'b0;
    #10 a=4'b0011;b=4'b0011;cin=1'b0;
    #10 a=4'b0100;b=4'b0100;cin=1'b0;
    #10 a=4'b0101;b=4'b0101;cin=1'b0;
    #10 a=4'b0110;b=4'b0110;cin=1'b0;
    #10 a=4'b0111;b=4'b0111;cin=1'b0;
    #10 a=4'b1000;b=4'b1000;cin=1'b0;
    #10 a=4'b1001;b=4'b1001;cin=1'b0;
    #10 a=4'b1010;b=4'b1010;cin=1'b0;
    #10 a=4'b1011;b=4'b1011;cin=1'b0;
    #10 a=4'b1100;b=4'b1100;cin=1'b0;
    #10 a=4'b1101;b=4'b1101;cin=1'b0;
    #10 a=4'b1110;b=4'b1110;cin=1'b0;
    #10 a=4'b1111;b=4'b1111;cin=1'b0;
    #10 $finish;
end
endmodule

Combinational/4 Bit FA/Structural_tb.vcd
$date
	Sun Jan 26 18:20:06 2025
$end
$version
	Icarus Verilog
$end
$timescale
	1ns
$end
$scope module Structural_tb $end
$var wire 1 ! cout $end
$var wire 4 " s [3:0] $end
$var reg 4 # a [3:0] $end
$var reg 4 $ b [3:0] $end
$var reg 1 % cin $end
$scope module uut $end
$var wire 4 & a [3:0] $end
$var wire 4 ' b [3:0] $end
$var wire 1 ( cin $end
$var wire 1 ! cout $end
$var wire 1 ) n1 $end
$var wire 1 * n2 $end
$var wire 1 + n3 $end
$var wire 4 , s [3:0] $end
$scope module f1 $end
$var wire 1 - N1 $end
$var wire 1 . N2 $end
$var wire 1 / N3 $end
$var wire 1 0 N4 $end
$var wire 1 1 a $end
$var wire 1 2 b $end
$var wire 1 ( cin $end
$var wire 1 ) cout $end
$var wire 1 3 sum $end
$upscope $end
$scope module f2 $end
$var wire 1 4 N1 $end
$var wire 1 5 N2 $end
$var wire 1 6 N3 $end
$var wire 1 7 N4 $end
$var wire 1 8 a $end
$var wire 1 9 b $end
$var wire 1 ) cin $end
$var wire 1 * cout $end
$var wire 1 : sum $end
$upscope $end
$scope module f3 $end
$var wire 1 ; N1 $end
$var wire 1 < N2 $end
$var wire 1 = N3 $end
$var wire 1 > N4 $end
$var wire 1 ? a $end
$var wire 1 @ b $end
$var wire 1 * cin $end
$var wire 1 + cout $end
$var wire 1 A sum $end
$upscope $end
$scope module f4 $end
$var wire 1 B N1 $end
$var wire 1 C N2 $end
$var wire 1 D N3 $end
$var wire 1 E N4 $end
$var wire 1 F a $end
$var wire 1 G b $end
$var wire 1 + cin $end
$var wire 1 ! cout $end
$var wire 1 H sum $end
$upscope $end
$upscope $end
$upscope $end
$enddefinitions $end
#0
$dumpvars
0H
0G
0F
0E
0D
0C
0B
0A
0@
0?
0>
0=
0<
0;
0:
09
08
07
06
05
04
03
02
01
00
0/
0.
0-
b0 ,
0+
0*
0)
0(
b0 '
b0 &
0%
b0 $
b0 #
b0 "
0!
$end
#10
1:
b10 "
b10 ,
1)
1.
12
11
b1 $
b1 '
b1 #
b1 &
#20
0:
1A
b100 "
b100 ,
0)
1*
06
0.
15
07
02
19
01
18
b10 $
b10 '
b10 #
b10 &
#30
1:
b110 "
b110 ,
16
17
1)
1.
12
11
b11 $
b11 '
b11 #
b11 &
#40
0:
0A
1H
b1000 "
b1000 ,
0)
0*
1+
06
0=
0.
05
07
1<
0>
02
09
1@
01
08
1?
b100 $
b100 '
b100 #
b100 &
#50
1:
b1010 "
b1010 ,
1)
1.
12
11
b101 $
b101 '
b101 #
b101 &
#60
0:
1A
b1100 "
b1100 ,
1=
1>
0)
1*
06
0.
15
07
02
19
01
18
b110 $
b110 '
b110 #
b110 &
#70
1:
b1110 "
b1110 ,
16
17
1)
1.
12
11
b111 $
b111 '
b111 #
b111 &
#80
0:
0A
0H
b0 "
b0 ,
0)
0*
0+
1!
06
0=
0D
0.
05
07
0<
0>
1C
0E
02
09
0@
1G
01
08
0?
1F
b1000 $
b1000 '
b1000 #
b1000 &
#90
1:
b10 "
b10 ,
1)
1.
12
11
b1001 $
b1001 '
b1001 #
b1001 &
#100
0:
1A
b100 "
b100 ,
0)
1*
06
0.
15
07
02
19
01
18
b1010 $
b1010 '
b1010 #
b1010 &
#110
1:
b110 "
b110 ,
16
17
1)
1.
12
11
b1011 $
b1011 '
b1011 #
b1011 &
#120
0:
0A
1H
b1000 "
b1000 ,
1D
1E
0)
0*
1+
06
0=
0.
05
07
1<
0>
02
09
1@
01
08
1?
b1100 $
b1100 '
b1100 #
b1100 &
#130
1:
b1010 "
b1010 ,
1)
1.
12
11
b1101 $
b1101 '
b1101 #
b1101 &
#140
0:
1A
b1100 "
b1100 ,
1=
1>
0)
1*
06
0.
15
07
02
19
01
18
b1110 $
b1110 '
b1110 #
b1110 &
#150
1:
b1110 "
b1110 ,
16
17
1)
1.
12
11
b1111 $
b1111 '
b1111 #
b1111 &
