Sequntial/Latch And Flipflops/DLatch/B_Async_Reset.v
module Behavioural_Async_Reset(q,d,en,rst);
input d,en,rst;
output reg q;

always@(en,d,rst)
    if(rst) q=0;
    else if(en) q=d;

endmodule

Sequntial/Latch And Flipflops/DLatch/B_A_R_tb.v
`timescale 1ns / 1ps
module Behavioural_Async_Reset_tb;
    reg d, en, rst;
    wire q;
    
    // Instantiate the D Latch module with async reset
    Behavioural_Async_Reset uut (.q(q), .d(d), .en(en), .rst(rst));
    
    initial begin
        $dumpfile("Behavioural_Async_Reset.vcd");
        $dumpvars(0, Behavioural_Async_Reset_tb);
        
        $monitor("Time=%0t | d=%b, en=%b, rst=%b -> q=%b", $time, d, en, rst, q);
        
        // Test cases
        #0  d = 0; en = 0; rst = 0; // Initial state
        #10 d = 1; en = 0; rst = 0; // Latch should hold previous value (undefined initially)
        #10 d = 1; en = 1; rst = 0; // Q should update to 1
        #10 d = 0; en = 1; rst = 0; // Q should update to 0
        #10 d = 1; en = 1; rst = 0; // Q should update to 1
        #10 d = 0; en = 0; rst = 0; // Q should hold previous value (1)
        #10 d = 1; en = 0; rst = 1; // Reset active, Q should be 0
        #10 d = 0; en = 1; rst = 1; // Reset active, Q should remain 0
        #10 d = 1; en = 1; rst = 0; // Q should update to 1
        #10 d = 0; en = 0; rst = 0; // Q should hold previous value (1)
        
        #10 $finish;
    end
endmodule

Sequntial/Latch And Flipflops/DLatch/Behavioural_Async_Reset.vcd
$date
	Sun Feb 02 13:33:56 2025
$end
$version
	Icarus Verilog
$end
$timescale
	1ps
$end
$scope module Behavioural_Async_Reset_tb $end
$var wire 1 ! q $end
$var reg 1 " d $end
$var reg 1 # en $end
$var reg 1 $ rst $end
$scope module uut $end
$var wire 1 % d $end
$var wire 1 & en $end
$var wire 1 ' rst $end
$var reg 1 ( q $end
$upscope $end
$upscope $end
$enddefinitions $end
#0
$dumpvars
x(
0'
0&
0%
0$
0#
0"
x!
$end
#10000
1"
1%
#20000
1(
1!
1#
1&
#30000
0(
0!
0"
0%
#40000
1(
1!
1"
1%
#50000
0#
0&
0"
0%
#60000
0(
0!
1$
1'
1"
1%
#70000
1#
1&
0"
0%
#80000
1(
1!
0$
0'
1"
1%
#90000
0#
0&
0"
0%
