Sequntial/Latch And Flipflops/DLatch/dataflow.v
module Dataflow(q,d,en);
input d,en;
output q;
assign q=en?d:q;
endmodule

Sequntial/Latch And Flipflops/DLatch/d_tb.v
`timescale 1ns / 1ps
module Dataflow_tb;
    reg d, en;
    wire q;
    
    // Instantiate the D Latch module
    Dataflow uut (.q(q), .d(d), .en(en));
    
    initial begin
        $dumpfile("Dataflow.vcd");
        $dumpvars(0, Dataflow_tb);
        
        $monitor("Time=%0t | d=%b, en=%b -> q=%b", $time, d, en, q);
        
        // Test cases
        #0  d = 0; en = 0;
        #10 d = 1; en = 0;
        #10 d = 1; en = 1;
        #10 d = 0; en = 1;
        #10 d = 1; en = 1;
        #10 d = 0; en = 0;
        #10 d = 1; en = 0;
        #10 d = 0; en = 1;
        #10 d = 1; en = 1;
        #10 d = 0; en = 0;
        
        #10 $finish;
    end
endmodule

Sequntial/Latch And Flipflops/DLatch/Dataflow.vcd
$date
	Sun Feb 02 13:22:08 2025
$end
$version
	Icarus Verilog
$end
$timescale
	1ps
$end
$scope module Dataflow_tb $end
$var wire 1 ! q $end
$var reg 1 " d $end
$var reg 1 # en $end
$scope module uut $end
$var wire 1 $ d $end
$var wire 1 % en $end
$var wire 1 ! q $end
$upscope $end
$upscope $end
$enddefinitions $end
#0
$dumpvars
0%
0$
0#
0"
x!
$end
#10000
1"
1$
#20000
1!
1#
1%
#30000
0!
0"
0$
#40000
1!
1"
1$
#50000
0#
0%
0"
0$
#60000
1"
1$
#70000
0!
1#
1%
0"
0$
#80000
1!
1"
1$
#90000
0#
0%
0"
0$
