Combinational/Decoder/2_4/Behavioural.v
module Behavioural(I, Y, EN);
    input [1:0] I;
    input EN;
    output reg [3:0] Y;  // FIXED: Y must be reg
    
    always @(*) begin
        if (EN) begin
            case (I)
                2'b00: Y = 4'b0001;
                2'b01: Y = 4'b0010;
                2'b10: Y = 4'b0100;
                2'b11: Y = 4'b1000;
                default: Y = 4'b0000; // Should never happen
            endcase
        end else begin
            Y = 4'b0000;  // FIXED: Output should be 0000 when EN=0
        end
    end
endmodule

Combinational/Decoder/2_4/Behavioural_tb.v
module Behavioural_tb;
reg [1:0]I;
reg EN;
wire [3:0]Y;
Behavioural uut(.I(I),.Y(Y),.EN(EN));
initial begin
    $dumpfile("Behavioural.vcd");
    $dumpvars(0,Behavioural_tb);

    $monitor("I=%b EN=%b Y=%b",I,EN,Y);
    #0 I=2'b00; EN=1'b1;
    #10 I=2'b01; EN=1'b1;
    #10 I=2'b10; EN=1'b1;
    #10 I=2'b11; EN=1'b1;
    #10 I=2'b00; EN=1'b0;
    #10 I=2'b01; EN=1'b0;
    #10 I=2'b10; EN=1'b0;
    #10 I=2'b11; EN=1'b0;
    #10 $finish;
end
endmodule

Combinational/Decoder/2_4/Behavioural.vcd
$date
	Wed Jan 29 18:35:59 2025
$end
$version
	Icarus Verilog
$end
$timescale
	1s
$end
$scope module Behavioural_tb $end
$var wire 4 ! Y [3:0] $end
$var reg 1 " EN $end
$var reg 2 # I [1:0] $end
$scope module uut $end
$var wire 1 $ EN $end
$var wire 2 % I [1:0] $end
$var reg 4 & Y [3:0] $end
$upscope $end
$upscope $end
$enddefinitions $end
#0
$dumpvars
b1 &
b0 %
1$
b0 #
1"
b1 !
$end
#10
b10 &
b10 !
b1 #
b1 %
#20
b100 &
b100 !
b10 #
b10 %
#30
b1000 &
b1000 !
b11 #
b11 %
#40
b0 &
b0 !
0"
0$
b0 #
b0 %
#50
b1 #
b1 %
#60
b10 #
b10 %
#70
b11 #
b11 %
