Sequntial/Counter/Modulus.v
module Counter_Modulus47_up(count,clk,rst,data);
input clk,rst;
input [7:0] data;
output [7:0] count;
reg [7:0] count_tmp;

always @ (posedge clk)
begin
    if(!rst || count_tmp>=8'd46) //Active Low
        count_tmp <= 8'd0;
    else
        count_tmp <= count_tmp + 1;
end
assign count = count_tmp;
endmodule

Sequntial/Counter/Modulus_tb.v
`timescale 1ns / 1ps

module Counter_Modulus47_up_tb;
    reg clk, rst;
    reg [7:0] data; // Not used in the module, included for completeness
    wire [7:0] count;

    // Instantiate the Design Under Test (DUT)
    Counter_Modulus47_up uut (
        .count(count),
        .clk(clk),
        .rst(rst),
        .data(data)
    );

    // Clock Generation (10ns period -> 5ns high, 5ns low)
    always #5 clk = ~clk;

    initial begin
        $dumpfile("Counter_Modulus47_up_tb.vcd"); // Generate waveform file
        $dumpvars(0, Counter_Modulus47_up_tb);
        $monitor("Time=%0t | Reset=%b | Count=%d", $time, rst, count);

        // Initialize signals
        clk = 0;
        rst = 0;  // Active Low Reset (forces count to 0)
        data = 8'd0;

        #10 rst = 1; // Release Reset, Counter starts counting
        #500; // Allow counter to reach 46 and wrap around

        // Apply Reset in middle of operation
        #10 rst = 0;
        #10 rst = 1; // Counter restarts

        #200;
        $finish; // End Simulation
    end
endmodule

Sequntial/Counter/Counter_Modulus47_up_tb.vcd
$date
	Sun Feb 09 10:43:46 2025
$end
$version
	Icarus Verilog
$end
$timescale
	1ps
$end
$scope module Counter_Modulus47_up_tb $end
$var wire 8 ! count [7:0] $end
$var reg 1 " clk $end
$var reg 8 # data [7:0] $end
$var reg 1 $ rst $end
$scope module uut $end
$var wire 1 % clk $end
$var wire 8 & count [7:0] $end
$var wire 8 ' data [7:0] $end
$var wire 1 ( rst $end
$var reg 8 ) count_tmp [7:0] $end
$upscope $end
$upscope $end
$enddefinitions $end
#0
$dumpvars
bx )
0(
b0 '
bx &
0%
0$
b0 #
0"
bx !
$end
#5000
b0 )
b0 !
b0 &
1"
1%
#10000
0"
0%
1$
1(
#15000
b1 )
b1 !
b1 &
1"
1%
#20000
0"
0%
#25000
b10 )
b10 !
b10 &
1"
1%
#30000
0"
0%
#35000
b11 )
b11 !
b11 &
1"
1%
#40000
0"
0%
#45000
b100 )
b100 !
b100 &
1"
1%
#50000
0"
0%
#55000
b101 )
b101 !
b101 &
1"
1%
#60000
0"
0%
#65000
b110 )
b110 !
b110 &
1"
1%
#70000
0"
0%
#75000
b111 )
b111 !
b111 &
1"
1%
#80000
0"
0%
#85000
b1000 )
b1000 !
b1000 &
1"
1%
#90000
0"
0%
#95000
b1001 )
b1001 !
b1001 &
1"
1%
#100000
0"
0%
#105000
b1010 )
b1010 !
b1010 &
1"
1%
#110000
0"
0%
#115000
b1011 )
b1011 !
b1011 &
1"
1%
#120000
0"
0%
#125000
b1100 )
b1100 !
b1100 &
1"
1%
#130000
0"
0%
#135000
b1101 )
b1101 !
b1101 &
1"
1%
#140000
0"
0%
#145000
b1110 )
b1110 !
b1110 &
1"
1%
#150000
0"
0%
#155000
b1111 )
b1111 !
b1111 &
1"
1%
#160000
0"
0%
#165000
b10000 )
b10000 !
b10000 &
1"
1%
#170000
0"
0%
#175000
b10001 )
b10001 !
b10001 &
1"
1%
#180000
0"
0%
#185000
b10010 )
b10010 !
b10010 &
1"
1%
#190000
0"
0%
#195000
b10011 )
b10011 !
b10011 &
1"
1%
#200000
0"
0%
#205000
b10100 )
b10100 !
b10100 &
1"
1%
#210000
0"
0%
#215000
b10101 )
b10101 !
b10101 &
1"
1%
#220000
0"
0%
#225000
b10110 )
b10110 !
b10110 &
1"
1%
#230000
0"
0%
#235000
b10111 )
b10111 !
b10111 &
1"
1%
#240000
0"
0%
#245000
b11000 )
b11000 !
b11000 &
1"
1%
#250000
0"
0%
#255000
b11001 )
b11001 !
b11001 &
1"
1%
#260000
0"
0%
#265000
b11010 )
b11010 !
b11010 &
1"
1%
#270000
0"
0%
#275000
b11011 )
b11011 !
b11011 &
1"
1%
#280000
0"
0%
#285000
b11100 )
b11100 !
b11100 &
1"
1%
#290000
0"
0%
#295000
b11101 )
b11101 !
b11101 &
1"
1%
#300000
0"
0%
#305000
b11110 )
b11110 !
b11110 &
1"
1%
#310000
0"
0%
#315000
b11111 )
b11111 !
b11111 &
1"
1%
#320000
0"
0%
#325000
b100000 )
b100000 !
b100000 &
1"
1%
#330000
0"
0%
#335000
b100001 )
b100001 !
b100001 &
1"
1%
#340000
0"
0%
#345000
b100010 )
b100010 !
b100010 &
1"
1%
#350000
0"
0%
#355000
b100011 )
b100011 !
b100011 &
1"
1%
#360000
0"
0%
#365000
b100100 )
b100100 !
b100100 &
1"
1%
#370000
0"
0%
#375000
b100101 )
b100101 !
b100101 &
1"
1%
#380000
0"
0%
#385000
b100110 )
b100110 !
b100110 &
1"
1%
#390000
0"
0%
#395000
b100111 )
b100111 !
b100111 &
1"
1%
#400000
0"
0%
#405000
b101000 )
b101000 !
b101000 &
1"
1%
#410000
0"
0%
#415000
b101001 )
b101001 !
b101001 &
1"
1%
#420000
0"
0%
#425000
b101010 )
b101010 !
b101010 &
1"
1%
#430000
0"
0%
#435000
b101011 )
b101011 !
b101011 &
1"
1%
#440000
0"
0%
#445000
b101100 )
b101100 !
b101100 &
1"
1%
#450000
0"
0%
#455000
b101101 )
b101101 !
b101101 &
1"
1%
#460000
0"
0%
#465000
b101110 )
b101110 !
b101110 &
1"
1%
#470000
0"
0%
#475000
b0 )
b0 !
b0 &
1"
1%
#480000
0"
0%
#485000
b1 )
b1 !
b1 &
1"
1%
#490000
0"
0%
#495000
b10 )
b10 !
b10 &
1"
1%
#500000
0"
0%
#505000
b11 )
b11 !
b11 &
1"
1%
#510000
0"
0%
#515000
b100 )
b100 !
b100 &
1"
1%
#520000
0"
0%
0$
0(
#525000
b0 )
b0 !
b0 &
1"
1%
#530000
0"
0%
1$
1(
#535000
b1 )
b1 !
b1 &
1"
1%
#540000
0"
0%
#545000
b10 )
b10 !
b10 &
1"
1%
#550000
0"
0%
#555000
b11 )
b11 !
b11 &
1"
1%
#560000
0"
0%
#565000
b100 )
b100 !
b100 &
1"
1%
#570000
0"
0%
#575000
b101 )
b101 !
b101 &
1"
1%
#580000
0"
0%
#585000
b110 )
b110 !
b110 &
1"
1%
#590000
0"
0%
#595000
b111 )
b111 !
b111 &
1"
1%
#600000
0"
0%
#605000
b1000 )
b1000 !
b1000 &
1"
1%
#610000
0"
0%
#615000
b1001 )
b1001 !
b1001 &
1"
1%
#620000
0"
0%
#625000
b1010 )
b1010 !
b1010 &
1"
1%
#630000
0"
0%
#635000
b1011 )
b1011 !
b1011 &
1"
1%
#640000
0"
0%
#645000
b1100 )
b1100 !
b1100 &
1"
1%
#650000
0"
0%
#655000
b1101 )
b1101 !
b1101 &
1"
1%
#660000
0"
0%
#665000
b1110 )
b1110 !
b1110 &
1"
1%
#670000
0"
0%
#675000
b1111 )
b1111 !
b1111 &
1"
1%
#680000
0"
0%
#685000
b10000 )
b10000 !
b10000 &
1"
1%
#690000
0"
0%
#695000
b10001 )
b10001 !
b10001 &
1"
1%
#700000
0"
0%
#705000
b10010 )
b10010 !
b10010 &
1"
1%
#710000
0"
0%
#715000
b10011 )
b10011 !
b10011 &
1"
1%
#720000
0"
0%
#725000
b10100 )
b10100 !
b10100 &
1"
1%
