Sequntial/Counter/Basic_Counter.v
module Counter_Up(count, reset, clock);
input reset, clock;
output [7:0] count;
reg [7:0] count_tmp;

always @ (posedge clock)
     if(!reset) //Active Load
        count_tmp <= 8'd0;
     else
        count_tmp <= count_tmp + 1;
assign count = count_tmp;
endmodule

Sequntial/Counter/Basic_Counter_tb.v
`timescale 1ns / 1ps

module Counter_Up_tb;
    reg clock, reset;
    wire [7:0] count;

    // Instantiate the Counter Module
    Counter_Up uut (
        .count(count),
        .reset(reset),
        .clock(clock)
    );

    // Clock Generation (10ns period → 5ns HIGH, 5ns LOW)
    always #5 clock = ~clock; 

    initial begin
        $dumpfile("Counter_Up_tb.vcd"); // Generate waveform
        $dumpvars(0, Counter_Up_tb);
        $monitor("Time=%0t | Reset=%b | Count=%d", $time, reset, count);

        // Initialize signals
        clock = 0; 
        reset = 1; // Apply reset at start
        
        // Reset the counter
        #10 reset = 0; // Deactivate reset
        #20 reset = 1; // Release reset
    
        #100 $finish;
    end
endmodule

Sequntial/Counter/Counter_Up_tb.vcd
$date
	Sat Feb 08 12:28:39 2025
$end
$version
	Icarus Verilog
$end
$timescale
	1ps
$end
$scope module Counter_Up_tb $end
$var wire 8 ! count [7:0] $end
$var reg 1 " clock $end
$var reg 1 # reset $end
$scope module uut $end
$var wire 1 $ clock $end
$var wire 8 % count [7:0] $end
$var wire 1 & reset $end
$var reg 8 ' count_tmp [7:0] $end
$upscope $end
$upscope $end
$enddefinitions $end
#0
$dumpvars
bx '
1&
bx %
0$
1#
0"
bx !
$end
#5000
1"
1$
#10000
0"
0$
0#
0&
#15000
b0 '
b0 !
b0 %
1"
1$
#20000
0"
0$
#25000
1"
1$
#30000
0"
0$
1#
1&
#35000
b1 '
b1 !
b1 %
1"
1$
#40000
0"
0$
#45000
b10 '
b10 !
b10 %
1"
1$
#50000
0"
0$
#55000
b11 '
b11 !
b11 %
1"
1$
#60000
0"
0$
#65000
b100 '
b100 !
b100 %
1"
1$
#70000
0"
0$
#75000
b101 '
b101 !
b101 %
1"
1$
#80000
0"
0$
#85000
b110 '
b110 !
b110 %
1"
1$
#90000
0"
0$
#95000
b111 '
b111 !
b111 %
1"
1$
#100000
0"
0$
#105000
b1000 '
b1000 !
b1000 %
1"
1$
#110000
0"
0$
#115000
b1001 '
b1001 !
b1001 %
1"
1$
#120000
0"
0$
#125000
b1010 '
b1010 !
b1010 %
1"
1$
