Sequntial/Counter/Up_Down.v
module Counter_Up_Down(count ,u_d,load,reset,clock,data);
input u_d,load,reset,clock;
input [7:0] data;
output [7:0] count;
reg [7:0] count_tmp;

always @ (posedge clock)
begin
    if(!reset) //Active Low
        count_tmp <= 8'd0;
    else if(load) //Load Data
        count_tmp <= data;
    else if(u_d) //Increment
        count_tmp <= count_tmp + 1;
    else //Decrement
        count_tmp <= count_tmp - 1;
end
assign count = count_tmp;
endmodule

Sequntial/Counter/Up_Down_tb.v
`timescale 1ns / 1ps

module Counter_Up_Down_tb;
    reg clock, reset, load, u_d;
    reg [7:0] data;
    wire [7:0] count;

    // Instantiate the DUT (Design Under Test)
    Counter_Up_Down uut (
        .count(count),
        .u_d(u_d),
        .load(load),
        .reset(reset),
        .clock(clock),
        .data(data)
    );

    // Clock Generation (10ns Period)
    always #5 clock = ~clock;

    initial begin
        $dumpfile("Counter_Up_Down_tb.vcd"); // VCD file for waveform viewing
        $dumpvars(0, Counter_Up_Down_tb);
        $monitor("Time=%0t | Reset=%b | Load=%b | U_D=%b | Data=%d | Count=%d", 
                 $time, reset, load, u_d, data, count);

        // Initialize signals
        clock = 0;
        reset = 0;  // Active low reset
        load = 0;
        u_d = 1;  // Start with up count
        data = 8'd0;

        #10 reset = 1; // Release reset
        #10;

        // Up Counting
        #50;

        // Load a value into the counter
        #10 load = 1; data = 8'd100;
        #10 load = 0; // Stop loading

        // Continue up counting
        #40;

        // Switch to Down Counting
        #10 u_d = 0;
        #50;

        // Load a new value into the counter
        #10 load = 1; data = 8'd50;
        #10 load = 0;

        // Continue Down Counting
        #40;

        // Apply reset again
        #10 reset = 0;
        #10 reset = 1;

        // Count more after reset
        #50;

        // End simulation
        #20 $finish;
    end
endmodule

Sequntial/Counter/Counter_Up_Down_tb.vcd
$date
	Sun Feb 09 10:39:44 2025
$end
$version
	Icarus Verilog
$end
$timescale
	1ps
$end
$scope module Counter_Up_Down_tb $end
$var wire 8 ! count [7:0] $end
$var reg 1 " clock $end
$var reg 8 # data [7:0] $end
$var reg 1 $ load $end
$var reg 1 % reset $end
$var reg 1 & u_d $end
$scope module uut $end
$var wire 1 ' clock $end
$var wire 8 ( count [7:0] $end
$var wire 8 ) data [7:0] $end
$var wire 1 * load $end
$var wire 1 + reset $end
$var wire 1 , u_d $end
$var reg 8 - count_tmp [7:0] $end
$upscope $end
$upscope $end
$enddefinitions $end
#0
$dumpvars
bx -
1,
0+
0*
b0 )
bx (
0'
1&
0%
0$
b0 #
0"
bx !
$end
#5000
b0 -
b0 !
b0 (
1"
1'
#10000
0"
0'
1%
1+
#15000
b1 -
b1 !
b1 (
1"
1'
#20000
0"
0'
#25000
b10 -
b10 !
b10 (
1"
1'
#30000
0"
0'
#35000
b11 -
b11 !
b11 (
1"
1'
#40000
0"
0'
#45000
b100 -
b100 !
b100 (
1"
1'
#50000
0"
0'
#55000
b101 -
b101 !
b101 (
1"
1'
#60000
0"
0'
#65000
b110 -
b110 !
b110 (
1"
1'
#70000
0"
0'
#75000
b111 -
b111 !
b111 (
1"
1'
#80000
0"
0'
b1100100 #
b1100100 )
1$
1*
#85000
b1100100 -
b1100100 !
b1100100 (
1"
1'
#90000
0"
0'
0$
0*
#95000
b1100101 -
b1100101 !
b1100101 (
1"
1'
#100000
0"
0'
#105000
b1100110 -
b1100110 !
b1100110 (
1"
1'
#110000
0"
0'
#115000
b1100111 -
b1100111 !
b1100111 (
1"
1'
#120000
0"
0'
#125000
b1101000 -
b1101000 !
b1101000 (
1"
1'
#130000
0"
0'
#135000
b1101001 -
b1101001 !
b1101001 (
1"
1'
#140000
0"
0'
0&
0,
#145000
b1101000 -
b1101000 !
b1101000 (
1"
1'
#150000
0"
0'
#155000
b1100111 -
b1100111 !
b1100111 (
1"
1'
#160000
0"
0'
#165000
b1100110 -
b1100110 !
b1100110 (
1"
1'
#170000
0"
0'
#175000
b1100101 -
b1100101 !
b1100101 (
1"
1'
#180000
0"
0'
#185000
b1100100 -
b1100100 !
b1100100 (
1"
1'
#190000
0"
0'
#195000
b1100011 -
b1100011 !
b1100011 (
1"
1'
#200000
0"
0'
b110010 #
b110010 )
1$
1*
#205000
b110010 -
b110010 !
b110010 (
1"
1'
#210000
0"
0'
0$
0*
#215000
b110001 -
b110001 !
b110001 (
1"
1'
#220000
0"
0'
#225000
b110000 -
b110000 !
b110000 (
1"
1'
#230000
0"
0'
#235000
b101111 -
b101111 !
b101111 (
1"
1'
#240000
0"
0'
#245000
b101110 -
b101110 !
b101110 (
1"
1'
#250000
0"
0'
#255000
b101101 -
b101101 !
b101101 (
1"
1'
#260000
0"
0'
0%
0+
#265000
b0 -
b0 !
b0 (
1"
1'
#270000
0"
0'
1%
1+
#275000
b11111111 -
b11111111 !
b11111111 (
1"
1'
#280000
0"
0'
#285000
b11111110 -
b11111110 !
b11111110 (
1"
1'
#290000
0"
0'
#295000
b11111101 -
b11111101 !
b11111101 (
1"
1'
#300000
0"
0'
#305000
b11111100 -
b11111100 !
b11111100 (
1"
1'
#310000
0"
0'
#315000
b11111011 -
b11111011 !
b11111011 (
1"
1'
#320000
0"
0'
#325000
b11111010 -
b11111010 !
b11111010 (
1"
1'
#330000
0"
0'
#335000
b11111001 -
b11111001 !
b11111001 (
1"
1'
