Basics/Adders/Full Adder/FA_behavioural.v
module FA_behavioural(a,b,cin,sum,cout);
    input a,b,cin;
    output reg sum,cout;
    always @(a,b,cin) begin
        sum=a^b^cin;
        cout=(a&b)|(b&cin)|(a&cin);
    end
endmodule

Basics/Adders/Full Adder/FA_behavioural_tb.v
`timescale 1ns/1ns

module FA_behavioural_tb;

    // Inputs
    reg a;
    reg b;
    reg cin;

    // Outputs
    wire sum;
    wire cout;

    // Instantiate the Unit Under Test (UUT)
    FA_behavioural uut (
        .a(a),
        .b(b),
        .cin(cin),
        .sum(sum),
        .cout(cout)
    );

    // Testbench logic
    initial begin
        // Open a file to log the results
        $dumpfile("FA_behavioural_tb.vcd");
        $dumpvars(0, FA_behavioural_tb);

        // Test case 1: a = 0, b = 0, cin = 0
        a = 0; b = 0; cin = 0;
        #10; // Wait for 10 time units
        $display("a = %b, b = %b, cin = %b, cout = %b, sum = %b", a, b, cin, cout, sum);

        // Test case 2: a = 0, b = 0, cin = 1
        a = 0; b = 0; cin = 1;
        #10;
        $display("a = %b, b = %b, cin = %b, cout = %b, sum = %b", a, b, cin, cout, sum);

        // Test case 3: a = 0, b = 1, cin = 0
        a = 0; b = 1; cin = 0;
        #10;
        $display("a = %b, b = %b, cin = %b, cout = %b, sum = %b", a, b, cin, cout, sum);

        // Test case 4: a = 0, b = 1, cin = 1
        a = 0; b = 1; cin = 1;
        #10;
        $display("a = %b, b = %b, cin = %b, cout = %b, sum = %b", a, b, cin, cout, sum);

        // Test case 5: a = 1, b = 0, cin = 0
        a = 1; b = 0; cin = 0;
        #10;
        $display("a = %b, b = %b, cin = %b, cout = %b, sum = %b", a, b, cin, cout, sum);

        // Test case 6: a = 1, b = 0, cin = 1
        a = 1; b = 0; cin = 1;
        #10;
        $display("a = %b, b = %b, cin = %b, cout = %b, sum = %b", a, b, cin, cout, sum);

        // Test case 7: a = 1, b = 1, cin = 0
        a = 1; b = 1; cin = 0;
        #10;
        $display("a = %b, b = %b, cin = %b, cout = %b, sum = %b", a, b, cin, cout, sum);

        // Test case 8: a = 1, b = 1, cin = 1
        a = 1; b = 1; cin = 1;
        #10;
        $display("a = %b, b = %b, cin = %b, cout = %b, sum = %b", a, b, cin, cout, sum);

        // End simulation
        $finish;
    end

endmodule

Basics/Adders/Full Adder/FA_behavioural_tb.vcd
$date
	Thu Jan 23 15:29:07 2025
$end
$version
	Icarus Verilog
$end
$timescale
	1ns
$end
$scope module FA_behavioural_tb $end
$var wire 1 ! cout $end
$var wire 1 " sum $end
$var reg 1 # a $end
$var reg 1 $ b $end
$var reg 1 % cin $end
$scope module uut $end
$var wire 1 & a $end
$var wire 1 ' b $end
$var wire 1 ( cin $end
$var reg 1 ) cout $end
$var reg 1 * sum $end
$upscope $end
$upscope $end
$enddefinitions $end
#0
$dumpvars
0*
0)
0(
0'
0&
0%
0$
0#
0"
0!
$end
#10
1*
1"
1%
1(
#20
0%
0(
1$
1'
#30
1)
1!
0*
0"
1%
1(
#40
0)
0!
1*
1"
0%
0(
0$
0'
1#
1&
#50
1)
1!
0*
0"
1%
1(
#60
0%
0(
1$
1'
#70
1*
1"
1%
1(
