Basics/Adders/Half Adder/HalfAdder.v
module HA(a,b,s,c);
 input a,b;
 output s,c;
 assign s=a^b;
 assign c=a&b;


endmodule

Basics/Adders/Full Adder/FA_using_HA.v
module FA_using_HA(a, b, Cin, Cout, sum);
    input a, b, Cin;
    output Cout, sum;
    wire N1, N2, N3;

    // Instantiate Half Adders
    HA HA1(.a(a), .b(b), .s(N1), .c(N2)); // First Half Adder
    HA HA2(.a(N1), .b(Cin), .s(sum), .c(N3)); // Second Half Adder

    // OR gate for Cout
    or or1(Cout, N2, N3);
endmodule

Basics/Adders/Full Adder/FA_using_HA_tb.v
`timescale 1ns/1ns

module FA_using_HA_tb;

    // Inputs
    reg a;
    reg b;
    reg Cin;

    // Outputs
    wire Cout;
    wire sum;

    // Instantiate the Unit Under Test (UUT)
    FA_using_HA uut (
        .a(a),
        .b(b),
        .Cin(Cin),
        .Cout(Cout),
        .sum(sum)
    );

    // Testbench logic
    initial begin
        // Open a file to log the results
        $dumpfile("FA_using_HA_tb.vcd");
        $dumpvars(0, FA_using_HA_tb);

        // Test case 1: a = 0, b = 0, Cin = 0
        a = 0; b = 0; Cin = 0;
        #10; // Wait for 10 time units
        $display("a = %b, b = %b, Cin = %b, Cout = %b, sum = %b", a, b, Cin, Cout, sum);

        // Test case 2: a = 0, b = 0, Cin = 1
        a = 0; b = 0; Cin = 1;
        #10;
        $display("a = %b, b = %b, Cin = %b, Cout = %b, sum = %b", a, b, Cin, Cout, sum);

        // Test case 3: a = 0, b = 1, Cin = 0
        a = 0; b = 1; Cin = 0;
        #10;
        $display("a = %b, b = %b, Cin = %b, Cout = %b, sum = %b", a, b, Cin, Cout, sum);

        // Test case 4: a = 0, b = 1, Cin = 1
        a = 0; b = 1; Cin = 1;
        #10;
        $display("a = %b, b = %b, Cin = %b, Cout = %b, sum = %b", a, b, Cin, Cout, sum);

        // Test case 5: a = 1, b = 0, Cin = 0
        a = 1; b = 0; Cin = 0;
        #10;
        $display("a = %b, b = %b, Cin = %b, Cout = %b, sum = %b", a, b, Cin, Cout, sum);

        // Test case 6: a = 1, b = 0, Cin = 1
        a = 1; b = 0; Cin = 1;
        #10;
        $display("a = %b, b = %b, Cin = %b, Cout = %b, sum = %b", a, b, Cin, Cout, sum);

        // Test case 7: a = 1, b = 1, Cin = 0
        a = 1; b = 1; Cin = 0;
        #10;
        $display("a = %b, b = %b, Cin = %b, Cout = %b, sum = %b", a, b, Cin, Cout, sum);

        // Test case 8: a = 1, b = 1, Cin = 1
        a = 1; b = 1; Cin = 1;
        #10;
        $display("a = %b, b = %b, Cin = %b, Cout = %b, sum = %b", a, b, Cin, Cout, sum);

        // End simulation
        $finish;
    end

endmodule

Basics/Adders/Full Adder/FA_using_HA_tb.vcd
$date
	Thu Jan 23 14:57:21 2025
$end
$version
	Icarus Verilog
$end
$timescale
	1ns
$end
$scope module FA_using_HA_tb $end
$var wire 1 ! Cout $end
$var wire 1 " sum $end
$var reg 1 # Cin $end
$var reg 1 $ a $end
$var reg 1 % b $end
$scope module uut $end
$var wire 1 & Cin $end
$var wire 1 ! Cout $end
$var wire 1 ' N1 $end
$var wire 1 ( N2 $end
$var wire 1 ) N3 $end
$var wire 1 * a $end
$var wire 1 + b $end
$var wire 1 " sum $end
$scope module HA1 $end
$var wire 1 * a $end
$var wire 1 + b $end
$var wire 1 ( c $end
$var wire 1 ' s $end
$upscope $end
$scope module HA2 $end
$var wire 1 ' a $end
$var wire 1 & b $end
$var wire 1 ) c $end
$var wire 1 " s $end
$upscope $end
$upscope $end
$upscope $end
$enddefinitions $end
#0
$dumpvars
0+
0*
0)
0(
0'
0&
0%
0$
0#
0"
0!
$end
#10
1"
1#
1&
#20
1'
0#
0&
1%
1+
#30
1!
0"
1)
1#
1&
#40
0!
1"
0)
0#
0&
0%
0+
1$
1*
#50
1!
0"
1)
1#
1&
#60
0)
0'
1(
0#
0&
1%
1+
#70
1"
1#
1&
