Basics/Adders/Full Adder/FullAdder.v
module FullAdder(a,b,cin,cout,sum);
    input a;
    input b;
    input cin;
    output cout;
    output sum;
    wire N1,N2,N3,N4;
    xor xor1(N1,a,b);
    xor xor2(sum,N1,cin);
    and and1(N2,a,b);
    and and2(N3,b,cin);
    and and3(N4,cin,a);
    or or1(cout,N2,N3,N4);
endmodule

Basics/Adders/Full Adder/FullAdder_tb.v
`timescale 1ns/1ns

module FullAdder_tb;

    // Inputs
    reg a;
    reg b;
    reg cin;

    // Outputs
    wire cout;
    wire sum;

    // Instantiate the Unit Under Test (UUT)
    FullAdder uut (
        .a(a),
        .b(b),
        .cin(cin),
        .cout(cout),
        .sum(sum)       
    ); // Semicolon added here

    // Testbench logic
    initial begin
        // Open a file to log the results
        $dumpfile("FullAdder_tb.vcd");
        $dumpvars(0, FullAdder_tb);

        // Test case 1: a = 0, b = 0, cin = 0
        a = 0; b = 0; cin = 0;
        #10; // Wait for 10 time units
        $display("a = %b, b = %b, cin = %b, cout = %b, sum = %b", a, b, cin, cout, sum);

        // Test case 2: a = 0, b = 0, cin = 1        
        a = 0; b = 0; cin = 1;
        #10; // Wait for 10 time units
        $display("a = %b, b = %b, cin = %b, cout = %b, sum = %b", a, b, cin, cout, sum);

        // Test case 3: a = 0, b = 1, cin = 0
        a = 0; b = 1; cin = 0;
        #10; // Wait for 10 time units
        $display("a = %b, b = %b, cin = %b, cout = %b, sum = %b", a, b, cin, cout, sum);

        // Test case 4: a = 0, b = 1, cin = 1
        a = 0; b = 1; cin = 1;
        #10; // Wait for 10 time units
        $display("a = %b, b = %b, cin = %b, cout = %b, sum = %b", a, b, cin, cout, sum);

        // Test case 5: a = 1, b = 0, cin = 0
        a = 1; b = 0; cin = 0;
        #10; // Wait for 10 time units
        $display("a = %b, b = %b, cin = %b, cout = %b, sum = %b", a, b, cin, cout, sum);

        // Test case 6: a = 1, b = 0, cin = 1
        a = 1; b = 0; cin = 1;
        #10; // Wait for 10 time units
        $display("a = %b, b = %b, cin = %b, cout = %b, sum = %b", a, b, cin, cout, sum);

        // Test case 7: a = 1, b = 1, cin = 0
        a = 1; b = 1; cin = 0;        
        #10; // Wait for 10 time units
        $display("a = %b, b = %b, cin = %b, cout = %b, sum = %b", a, b, cin, cout, sum);

        // Test case 8: a = 1, b = 1, cin = 1
        a = 1; b = 1; cin = 1;
        #10; // Wait for 10 time units
        $display("a = %b, b = %b, cin = %b, cout = %b, sum = %b", a, b, cin, cout, sum);

        // End simulation
        $finish;
    end

endmodule

Basics/Adders/Full Adder/FullAdder_tb.vcd
$date
	Thu Jan 23 11:29:13 2025
$end
$version
	Icarus Verilog
$end
$timescale
	1ns
$end
$scope module FullAdder_tb $end
$var wire 1 ! cout $end
$var wire 1 " sum $end
$var reg 1 # a $end
$var reg 1 $ b $end
$var reg 1 % cin $end
$scope module uut $end
$var wire 1 & N1 $end
$var wire 1 ' N2 $end
$var wire 1 ( N3 $end
$var wire 1 ) N4 $end
$var wire 1 * a $end
$var wire 1 + b $end
$var wire 1 , cin $end
$var wire 1 ! cout $end
$var wire 1 " sum $end
$upscope $end
$upscope $end
$enddefinitions $end
#0
$dumpvars
0,
0+
0*
0)
0(
0'
0&
0%
0$
0#
0"
0!
$end
#10
1"
1%
1,
#20
1&
0%
0,
1$
1+
#30
1!
0"
1(
1%
1,
#40
0!
1"
0(
0%
0,
0$
0+
1#
1*
#50
1!
0"
1)
1%
1,
#60
0)
0&
1'
0%
0,
1$
1+
#70
1"
1(
1)
1%
1,
