Combinational/Decoder/3_8/Dataflow.v
module Dataflow(I,Y,EN);
input [2:0] I;
input EN;
output [7:0] Y;

assign Y = {
    EN & I[2] & I[1] & I[0],
    EN & I[2] & I[1] & ~I[0],
    EN & I[2] & ~I[1] & I[0],
    EN & I[2] & ~I[1] & ~I[0],
    EN & ~I[2] & I[1] & I[0],
    EN & ~I[2] & I[1] & ~I[0],
    EN & ~I[2] & ~I[1] & I[0],
    EN & ~I[2] & ~I[1] & ~I[0]
};
endmodule

Combinational/Decoder/3_8/Dataflow_tb.v
module Dataflow_tb;
    reg [2:0] I;
    reg EN;
    wire [7:0] Y;

    Dataflow uut (.I(I), .Y(Y), .EN(EN));

    initial begin
        $dumpfile("Dataflow.vcd");
        $dumpvars(0, Dataflow_tb);

        $monitor("I=%b EN=%b Y=%b", I, EN, Y);
        
        // Test cases for EN = 1 (should activate one-hot encoding)
        #0  I=3'b000; EN=1'b1; // Y=00000001
        #10 I=3'b001; EN=1'b1; // Y=00000010
        #10 I=3'b010; EN=1'b1; // Y=00000100
        #10 I=3'b011; EN=1'b1; // Y=00001000
        #10 I=3'b100; EN=1'b1; // Y=00010000
        #10 I=3'b101; EN=1'b1; // Y=00100000
        #10 I=3'b110; EN=1'b1; // Y=01000000
        #10 I=3'b111; EN=1'b1; // Y=10000000
        
        // Test cases for EN = 0 (all outputs should be 00000000)
        #10 I=3'b000; EN=1'b0; // Y=00000000
        #10 I=3'b001; EN=1'b0; // Y=00000000
        #10 I=3'b010; EN=1'b0; // Y=00000000
        #10 I=3'b011; EN=1'b0; // Y=00000000
        #10 I=3'b100; EN=1'b0; // Y=00000000
        #10 I=3'b101; EN=1'b0; // Y=00000000
        #10 I=3'b110; EN=1'b0; // Y=00000000
        #10 I=3'b111; EN=1'b0; // Y=00000000
        
        #10 $finish;
    end
endmodule

Combinational/Decoder/3_8/Dataflow.vcd
$date
	Wed Jan 29 18:43:22 2025
$end
$version
	Icarus Verilog
$end
$timescale
	1s
$end
$scope module Dataflow_tb $end
$var wire 8 ! Y [7:0] $end
$var reg 1 " EN $end
$var reg 3 # I [2:0] $end
$scope module uut $end
$var wire 1 $ EN $end
$var wire 3 % I [2:0] $end
$var wire 8 & Y [7:0] $end
$upscope $end
$upscope $end
$enddefinitions $end
#0
$dumpvars
b1 &
b0 %
1$
b0 #
1"
b1 !
$end
#10
b10 !
b10 &
b1 #
b1 %
#20
b100 !
b100 &
b10 #
b10 %
#30
b1000 !
b1000 &
b11 #
b11 %
#40
b10000 !
b10000 &
b100 #
b100 %
#50
b100000 !
b100000 &
b101 #
b101 %
#60
b1000000 !
b1000000 &
b110 #
b110 %
#70
b10000000 !
b10000000 &
b111 #
b111 %
#80
b0 !
b0 &
0"
0$
b0 #
b0 %
#90
b1 #
b1 %
#100
b10 #
b10 %
#110
b11 #
b11 %
#120
b100 #
b100 %
#130
b101 #
b101 %
#140
b110 #
b110 %
#150
b111 #
b111 %
